easyspec_mods/__init__.py
easyspec_mods/__main__.py
easyspec_mods/cli.py
easyspec_mods/utils.py
easyspec_mods/analysis/__init__.py
easyspec_mods/analysis/analysis.py
easyspec_mods/analysis/lines/astro_lines.dat
easyspec_mods/cleaning/__init__.py
easyspec_mods/cleaning/cleaning.py
easyspec_mods/extraction/__init__.py
easyspec_mods/extraction/extraction.py
easyspec_mods/extraction/airmass/apo_airmass_extinction.txt
easyspec_mods/extraction/airmass/ctio_airmass_extinction.txt
easyspec_mods/extraction/airmass/kpno_airmass_extinction.txt
easyspec_mods/extraction/airmass/lapalma_airmass_extinction.txt
easyspec_mods/extraction/airmass/mko_airmass_extinction.txt
easyspec_mods/extraction/airmass/mtham_airmass_extinction.txt
easyspec_mods/extraction/airmass/paranal_airmass_extinction.txt
easyspec_mods/extraction/standards/blackbody/b.dat
easyspec_mods/extraction/standards/blackbody/h.dat
easyspec_mods/extraction/standards/blackbody/i.dat
easyspec_mods/extraction/standards/blackbody/j.dat
easyspec_mods/extraction/standards/blackbody/k.dat
easyspec_mods/extraction/standards/blackbody/l.dat
easyspec_mods/extraction/standards/blackbody/lprime.dat
easyspec_mods/extraction/standards/blackbody/m.dat
easyspec_mods/extraction/standards/blackbody/mkbbcal.cl
easyspec_mods/extraction/standards/blackbody/mkbbdat.cl
easyspec_mods/extraction/standards/blackbody/params.dat
easyspec_mods/extraction/standards/blackbody/r.dat
easyspec_mods/extraction/standards/blackbody/standards.men
easyspec_mods/extraction/standards/blackbody/u.dat
easyspec_mods/extraction/standards/blackbody/v.dat
easyspec_mods/extraction/standards/bstdscal/hr3454.dat
easyspec_mods/extraction/standards/bstdscal/hr3982.dat
easyspec_mods/extraction/standards/bstdscal/hr4468.dat
easyspec_mods/extraction/standards/bstdscal/hr4534.dat
easyspec_mods/extraction/standards/bstdscal/hr5191.dat
easyspec_mods/extraction/standards/bstdscal/hr5511.dat
easyspec_mods/extraction/standards/bstdscal/hr7001.dat
easyspec_mods-1.0.0.12.dist-info/METADATA
easyspec_mods-1.0.0.12.dist-info/WHEEL
easyspec_mods-1.0.0.12.dist-info/entry_points.txt
easyspec_mods-1.0.0.12.dist-info/RECORD
