Metadata-Version: 2.4
Name: easyspec-mods
Version: 1.0.0.12
Summary: easySpec is a library for the reduction, extraction, and analysis of long-slit astrophysical spectra.
Project-URL: Homepage, https://github.com/ranieremenezes/easyspec
Project-URL: Issues, https://github.com/ranieremenezes/easyspec
Project-URL: Contributions, https://buymeacoffee.com/easyfermi
Author-email: Raniere de Menezes <raniere.m.menezes@gmail.com>
License: BSD-3-Clause
Classifier: Operating System :: OS Independent
Classifier: Programming Language :: Python :: 3
Requires-Python: >=3.8
